copywriter/__init__.py
copywriter-0.0.1.dist-info/LICENSE
copywriter-0.0.1.dist-info/METADATA
copywriter-0.0.1.dist-info/WHEEL
copywriter-0.0.1.dist-info/RECORD
