Metadata-Version: 2.1
Name: copywriter
Version: 0.0.1
Summary: Automated content generation tailored to your voice.
License: Valentin Calomme <info@valentincalomme.com>
Author: Valentin Calomme
Author-email: valentin.calomme@klm.com
Requires-Python: >=3.12,<4.0
Classifier: License :: Other/Proprietary License
Classifier: Programming Language :: Python :: 3
Classifier: Programming Language :: Python :: 3.12
